README.md
setup.py
pke_zh/__init__.py
pke_zh/base.py
pke_zh/data_structures.py
pke_zh/keybert.py
pke_zh/multipartiterank.py
pke_zh/positionrank.py
pke_zh/readers.py
pke_zh/singlerank.py
pke_zh/textrank.py
pke_zh/tfidf.py
pke_zh/topicrank.py
pke_zh/version.py
pke_zh/wordrank.py
pke_zh/yake.py
pke_zh/yake_zh.py
pke_zh.egg-info/PKG-INFO
pke_zh.egg-info/SOURCES.txt
pke_zh.egg-info/dependency_links.txt
pke_zh.egg-info/not-zip-safe
pke_zh.egg-info/requires.txt
pke_zh.egg-info/top_level.txt
pke_zh/data/common_char_set.txt
pke_zh/data/entropy_word_score.json
pke_zh/data/person_name.txt
pke_zh/data/place_name.txt
pke_zh/data/pmi_word_score.json
pke_zh/data/stopwords.txt
pke_zh/utils/__init__.py
pke_zh/utils/file_utils.py
pke_zh/utils/io_utils.py
pke_zh/utils/text_utils.py
pke_zh/utils/tokenizer.py