Metadata-Version: 2.1
Name: pke-zh
Version: 0.2.5
Summary: pke_zh, context-aware bag-of-words term weights for query and document.
Home-page: https://github.com/shibing624/pke_zh
Author: XuMing
Author-email: xuming624@qq.com
License: Apache 2.0
Keywords: pke_zh,term weighting,textrank,word rank,wordweight
Platform: Windows
Platform: Linux
Platform: Solaris
Platform: Mac OS-X
Platform: Unix
Classifier: Intended Audience :: Developers
Classifier: Operating System :: OS Independent
Classifier: Natural Language :: Chinese (Simplified)
Classifier: Natural Language :: Chinese (Traditional)
Classifier: Programming Language :: Python
Classifier: Programming Language :: Python :: 3
Classifier: Topic :: Text Processing :: Linguistic
Classifier: Topic :: Scientific/Engineering :: Artificial Intelligence
Requires-Python: >=3.5
